{
  "$schema": "https://mintlify.com/schema.json",
  "name": "docs-verihubs",
  "logo": {
    "dark": "/logo/inverted.png",
    "light": "/logo/regular.png"
  },
  "favicon": "/favicon.svg",
  "colors": {
    "primary": "#20255e",
    "light": "#1a1e4b",
    "dark": "#20255e",
    "anchors": {
      "from": "#20255e",
      "to": "#1a1e4b"
    }
  },
  "topbarLinks": [
    {
      "name": "Jadwalkan Demo Gratis",
      "url": "https://verihubs.com/jadwalkan-demo-gratis"
    }
  ],
  "topbarCtaButton": {
    "name": "Lihat Produk",
    "url": "https://verihubs.com#product-list"
  },
  "tabs": [],
  "anchors": [],
  "modeToggle": {
    "default": "dark"
  },
  "navigation": [
    {
      "group": "Authentication",
      "pages": [
        "authentication/sign-up",
        "authentication/sign-in",
        "authentication/multiple-company-access"
      ]
    },
    {
      "group": "Regulations & Compliance",
      "pages": [
        "regulations-&-compliance/rate-limit",
        "regulations-&-compliance/service-level-agreement",
        "regulations-&-compliance/contact-us",
        "regulations-&-compliance/api-security-checklist"
      ]
    },
    {
      "group": "WhatsApp",
      "pages": [
        "whatsapp/whatsapp-get-started",
        "whatsapp/whatsapp-template",
        "whatsapp/whatsapp-otp",
        "whatsapp/whatsapp-notifications"
      ]
    },
    {
      "group": "SMS",
      "pages": [
        "sms/sms-otp",
        "sms/sms-announcement",
        "sms/sms-segment-count-explanation",
        "sms/sms-international-supported-countries",
        "sms/supported-local-operator-prefix"
      ]
    }
  ],
  "footerSocials": {
    "instagram": "https://www.instagram.com/verihubs/",
    "linkedin": "https://www.linkedin.com/company/verihubs/"
  }
}